airflow_provider_tm1/__init__.py
airflow_provider_tm1/hooks/__init__.py
airflow_provider_tm1/hooks/tm1.py
airflow_provider_tm1/operators/__init__.py
airflow_provider_tm1/operators/tm1_mdx_query.py
airflow_provider_tm1/operators/tm1_run_ti.py
airflow_provider_tm1/sensors/__init__.py
airflow_provider_tm1-0.5.1.dist-info/licenses/LICENSE
airflow_provider_tm1-0.5.1.dist-info/METADATA
airflow_provider_tm1-0.5.1.dist-info/WHEEL
airflow_provider_tm1-0.5.1.dist-info/entry_points.txt
airflow_provider_tm1-0.5.1.dist-info/top_level.txt
airflow_provider_tm1-0.5.1.dist-info/RECORD
