Metadata-Version: 2.4
Name: airflow-provider-tm1
Version: 0.5.1
Summary: A package to simplify connecting to the TM1 REST API from Apache Airflow
Author-email: Akos Andras Nagy <akos.nagy@knowledgeseed.ch>, Marius Wirtz <mwirtz@cubewise.com>
Maintainer-email: Akos Andras Nagy <akos.nagy@knowledgeseed.ch>, Marius Wirtz <mwirtz@cubewise.com>
License:                                  Apache License
Project-URL: Documentation, https://github.com/airflow-provider-tm1/airflow-provider-tm1/blob/master/README.md
Project-URL: Repository, https://github.com/airflow-provider-tm1/airflow-provider-tm1
Project-URL: Issues, https://github.com/airflow-provider-tm1/airflow-provider-tm1/issues
Project-URL: Changelog, https://github.com/airflow-provider-tm1/airflow-provider-tm1/CHANGELOG.md
Requires-Python: >=3.7
License-File: LICENSE
Requires-Dist: apache-airflow>=2.3
Requires-Dist: tm1py>=1.1
Dynamic: license-file
